README.rst
requirements.txt
setup.py
percent_encode_all/__init__.py
percent_encode_all.egg-info/PKG-INFO
percent_encode_all.egg-info/SOURCES.txt
percent_encode_all.egg-info/dependency_links.txt
percent_encode_all.egg-info/requires.txt
percent_encode_all.egg-info/top_level.txt