Metadata-Version: 1.1
Name: percent-encode-all
Version: 0.1.0
Summary: Encode every charactor into percent format.
Home-page: https://github.com/fx-kirin/percent_encode_all
Author: fx-kirin
Author-email: fx.kirin@gmail.com
License: MIT
Platform: UNKNOWN
Classifier: Development Status :: 2 - Pre-Alpha
Classifier: License :: OSI Approved :: MIT License
Classifier: Programming Language :: Python
Classifier: Programming Language :: Python :: 2
Classifier: Programming Language :: Python :: 2.7
Classifier: Programming Language :: Python :: 3
Classifier: Programming Language :: Python :: 3.4
Classifier: Programming Language :: Python :: 3.5
Classifier: Programming Language :: Python :: 3.6
Classifier: Programming Language :: Python :: 3.7
